{
  "answer": "(2, 1, 5, 3, 4, 6)",
  "choices": [
    "(2, 1, 4, 5, 3, 6)",
    "(2, 3, 1, 4, 5, 6)",
    "(2, 1, 5, 3, 4, 6)"
  ],
  "correct_choice_index": 2,
  "enabled": true,
  "explanation": "<div aria-atomic=\"true\" class=\"zb-explanation has-explanation correct\" role=\"alert\">\n <p class=\"message\">\n  Correct\n </p>\n The next permutation is found by swapping 4 and 5 and then reordering\n <span style=\"white-space: nowrap;\">\n  (\u2026, 6, 4, 3).\n </span>\n</div>\n",
  "images": {
    "choices": [
      "4.15.5.1-activity-choice-0.png",
      "4.15.5.1-activity-choice-1.png",
      "4.15.5.1-activity-choice-2.png"
    ],
    "explanation": "4.15.5-activity-explanation_div.png",
    "instructions": "4.15.5-activity-instructions_div.png",
    "question": "4.15.5.1-activity-question.png"
  },
  "input_type": "fieldset",
  "instructions": "<div class=\"activity-instructions\">\n</div>\n",
  "qid": 1,
  "question": "<div>\n <div class=\"text\">\n  What is the next permutation after (2, 1, 4, 6, 5, 3) in lexicographic order?\n </div>\n</div>",
  "section": "4.15.5: Finding the next permutation in lexicographic order."
}