{
  "answer": "101376",
  "choices": [],
  "correct_choice_index": null,
  "enabled": true,
  "explanation": null,
  "images": {
    "choices": [],
    "instructions": "4.8.3-exercise-instructions_div.png",
    "question": "4.8.3.1-exercise-question.png"
  },
  "input_type": null,
  "instructions": "<div class=\"setup\">\n <p>\n  How many different strings of length 12 containing exactly five a's can be chosen over the following alphabets?\n </p>\n</div>\n",
  "qid": 1,
  "question": "<div class=\"question\">\n <span class=\"part\">\n  (b)\n </span>\n <div class=\"text\">\n  <p>\n   The alphabet {a, b, c}\n  </p>\n </div>\n</div>\n",
  "section": "Exercise 4.8.3: Counting strings of letters."
}